meme_analysis/__init__.py
meme_analysis/meme_analysis.py
meme_analysis-1.0.4.dist-info/LICENSE
meme_analysis-1.0.4.dist-info/METADATA
meme_analysis-1.0.4.dist-info/WHEEL
meme_analysis-1.0.4.dist-info/top_level.txt
meme_analysis-1.0.4.dist-info/RECORD
