Metadata-Version: 2.1
Name: meme-analysis
Version: 1.0.4
Summary: Sememe Analysis by SIST(Shizuoka Institute of Science and Technology) NLP Lab XiaoranLi
Home-page: https://github.com/SauronLee/meme_analysis
Author: Xiaoran Li(李笑然)
Author-email: lixira@outlook.com
License: UNKNOWN
Platform: UNKNOWN
Classifier: Programming Language :: Python :: 3
Classifier: License :: OSI Approved :: Apache Software License
Classifier: Operating System :: OS Independent
